pibackbone/__init__.py
pibackbone/__main__.py
pibackbone/definitions.json
pibackbone/main.py
pibackbone/styles.py
pibackbone-0.4.5.data/data/opt/pibackbone/config.txt
pibackbone-0.4.5.data/data/opt/pibackbone/definitions.json
pibackbone-0.4.5.data/data/opt/pibackbone/install.sh
pibackbone-0.4.5.data/data/opt/pibackbone/scripts/shutdown.sh
pibackbone-0.4.5.data/data/opt/pibackbone/scripts/system_health.sh
pibackbone-0.4.5.data/data/opt/pibackbone/scripts/cron.d/pibackbone
pibackbone-0.4.5.data/data/opt/pibackbone/scripts/cron.d/pijuice
pibackbone-0.4.5.data/data/opt/pibackbone/services/.env
pibackbone-0.4.5.data/data/opt/pibackbone/services/docker-compose-cell-sim7600g-h.yml
pibackbone-0.4.5.data/data/opt/pibackbone/services/docker-compose-compass.yml
pibackbone-0.4.5.data/data/opt/pibackbone/services/docker-compose-core.yml
pibackbone-0.4.5.data/data/opt/pibackbone/services/docker-compose-daisy.yml
pibackbone-0.4.5.data/data/opt/pibackbone/services/docker-compose-environment-sensor.yml
pibackbone-0.4.5.data/data/opt/pibackbone/services/docker-compose-hifiberry-dac-plus-adc-pro.yml
pibackbone-0.4.5.data/data/opt/pibackbone/services/docker-compose-pijuice.yml
pibackbone-0.4.5.data/data/opt/pibackbone/services/docker-compose-s3-upload.yml
pibackbone-0.4.5.data/data/opt/pibackbone/services/docker-compose-sense.yml
pibackbone-0.4.5.data/data/opt/pibackbone/services/docker-compose-status-updater.yml
pibackbone-0.4.5.data/data/opt/pibackbone/services/cell-sim7600g-h/Dockerfile
pibackbone-0.4.5.data/data/opt/pibackbone/services/cell-sim7600g-h/start-modem.sh
pibackbone-0.4.5.data/data/opt/pibackbone/services/compass/Dockerfile
pibackbone-0.4.5.data/data/opt/pibackbone/services/compass/README.md
pibackbone-0.4.5.data/data/opt/pibackbone/services/compass/compass_app.py
pibackbone-0.4.5.data/data/opt/pibackbone/services/compass/requirements.txt
pibackbone-0.4.5.data/data/opt/pibackbone/services/compass/test_compass_app.py
pibackbone-0.4.5.dist-info/AUTHORS
pibackbone-0.4.5.dist-info/LICENSE
pibackbone-0.4.5.dist-info/METADATA
pibackbone-0.4.5.dist-info/WHEEL
pibackbone-0.4.5.dist-info/entry_points.txt
pibackbone-0.4.5.dist-info/pbr.json
pibackbone-0.4.5.dist-info/top_level.txt
pibackbone-0.4.5.dist-info/RECORD
