Metadata-Version: 2.1
Name: pibackbone
Version: 0.4.5
Summary: A tool for installing the backbone pieces of any Pi-based project
Home-page: https://github.com/IQTLabs/PiBackbone
Author: cglewis
Author-email: clewis@iqt.org
License: Apache-2
Platform: any
Classifier: Development Status :: 2 - Pre-Alpha
Classifier: License :: OSI Approved :: Apache Software License
Classifier: Programming Language :: Python
Requires-Python: >=3.6
Requires-Dist: docker-compose (==1.29.2)
Requires-Dist: docker (==6.0.0)
Requires-Dist: inquirerpy (==0.3.4)
Requires-Dist: pbr (==5.10.0)
Requires-Dist: plumbum (==1.7.2)
